blake2b_py-0.3.2.dist-info/METADATA
blake2b_py-0.3.2.dist-info/WHEEL
blake2b/__init__.py
blake2b/blake2b.cp39-win_amd64.pyd
blake2b_py-0.3.2.dist-info/RECORD
