Metadata-Version: 2.4
Name: blake2b-py
Version: 0.3.2
Summary: Blake2b hashing in Rust with Python bindings.
Author: David Sanders <davesque@gmail.com>
Author-email: David Sanders <davesque@gmail.com>
License: MIT
Project-URL: Source Code, https://github.com/ethereum/blake2b-py
